reprexpy/__init__.py
reprexpy/reprex.py
reprexpy/session_info.py
reprexpy/examples/basic-example.py
reprexpy/examples/error.py
reprexpy/examples/plotting.py
reprexpy-0.3.3.dist-info/LICENSE.txt
reprexpy-0.3.3.dist-info/METADATA
reprexpy-0.3.3.dist-info/WHEEL
reprexpy-0.3.3.dist-info/top_level.txt
reprexpy-0.3.3.dist-info/RECORD
