Metadata-Version: 2.1
Name: reprexpy
Version: 0.3.3
Summary: Render reproducible examples of Python code (port of R package `reprex`)
Home-page: https://reprexpy.readthedocs.io/en/latest
Author: Christopher Baker
Author-email: chriscrewbaker@gmail.com
License: LICENSE.txt
Requires-Python: >=3.8
License-File: LICENSE.txt
Requires-Dist: pyperclip
Requires-Dist: asttokens
Requires-Dist: nbconvert
Requires-Dist: nbformat
Requires-Dist: matplotlib
Requires-Dist: ipython
Requires-Dist: pyimgur
Requires-Dist: stdlib-list
Requires-Dist: ipykernel
Requires-Dist: tornado
